packTab/__init__.py
packTab/__main__.py
packtab-0.1.0.dist-info/LICENSE
packtab-0.1.0.dist-info/METADATA
packtab-0.1.0.dist-info/WHEEL
packtab-0.1.0.dist-info/top_level.txt
packtab-0.1.0.dist-info/RECORD
