Metadata-Version: 2.1
Name: packtab
Version: 0.1.0
Summary: Unicode (and other integer) table packer
Home-page: https://github.com/harfbuzz/packtab
Author: Behdad Esfahbod
Author-email: behdad@behdad.org
License: Apache Software License 2.0
Platform: any
Classifier: Development Status :: 3 - Alpha
Classifier: Intended Audience :: Developers
Classifier: Operating System :: OS Independent
Classifier: Programming Language :: Python :: 3
Classifier: Programming Language :: Python :: 3.5
Classifier: Programming Language :: Python :: 3.6
Classifier: Programming Language :: Python :: 3.7
Requires-Python: >=3.5
